setup.cfg
setup.py
sofa/__init__.py
sofa/config.py
sofa/exceptions.py
sofa/parser.py
sofa/readers.py
sofa/responses.py
sofa/structure.py
sofa/tools.py
sofa/tree.py
sofa/types.py
sofa/validators.py
sofa/views.py
sofa/writers.py
sofa.egg-info/PKG-INFO
sofa.egg-info/SOURCES.txt
sofa.egg-info/dependency_links.txt
sofa.egg-info/entry_points.txt
sofa.egg-info/requires.txt
sofa.egg-info/top_level.txt
sofa/scripts/__init__.py
sofa/scripts/js.py