Metadata-Version: 1.1
Name: sofa
Version: 0.7.4
Summary: A lightweight REST API framework
Home-page: https://github.com/reberhardt/sofa
Author: Ryan Eberhardt
Author-email: ryan@reberhardt.com
License: UNKNOWN
Download-URL: https://github.com/reberhardt/sofa/tarball/0.7.4
Keywords: rest,api
Platform: UNKNOWN
